{
  "project_info": {
    "project_number": "971585166326",
    "firebase_url": "https://inventoria-90e78-default-rtdb.firebaseio.com",
    "project_id": "inventoria-90e78",
    "storage_bucket": "inventoria-90e78.firebasestorage.app"
  },
  "client": [
    {
      "client_info": {
        "mobilesdk_app_id": "1:971585166326:android:f9a854a3a31abda87ac5d7",
        "android_client_info": {
          "package_name": "com.example.jjsminventorias"
        }
      },
      "oauth_client": [
        {
          "client_id": "971585166326-m1pfi6cnhu2o3ops1o8sbqquf28ugia2.apps.googleusercontent.com",
          "client_type": 3
        }
      ],
      "api_key": [
        {
          "current_key": "AIzaSyDyIgXcOVuyv7UGam8L-JrLo2dBcMfHWM0"
        }
      ],
      "services": {
        "appinvite_service": {
          "other_platform_oauth_client": [
            {
              "client_id": "971585166326-m1pfi6cnhu2o3ops1o8sbqquf28ugia2.apps.googleusercontent.com",
              "client_type": 3
            }
          ]
        }
      }
    }
  ],
  "configuration_version": "1"
}